iotprovision/__init__.py
iotprovision/config.py
iotprovision/deprecated.py
iotprovision/eccstorage.py
iotprovision/firmwareinterface.py
iotprovision/iotprovision.py
iotprovision/iotprovision_main.py
iotprovision/kit_config.py
iotprovision/logfilters.py
iotprovision/logging.yaml
iotprovision/provisioner.py
iotprovision/winc_root_certs.py
iotprovision/aws/__init__.py
iotprovision/aws/custom_provision.py
iotprovision/aws/sandbox_provision.py
iotprovision/azure/__init__.py
iotprovision/azure/custom_provision.py
iotprovision/cellular/__init__.py
iotprovision/cellular/atprovisioner.py
iotprovision/cellular/cellularprovisioner.py
iotprovision/cellular/sequans_ciphersuites.py
iotprovision/fw/nedbg_fw.zip
iotprovision/fw/winc/WINC1500_19.7.6.bin
iotprovision/fw/winc/WINC1500_19.7.7.bin
iotprovision/fw/winc/tls_root_cert.bin
iotprovision/winc/__init__.py
iotprovision/winc/pywinc.py
iotprovision/winc/pywinc_main.py
iotprovision/winc/winc_certs.py
iotprovision/winc/winc_flash_map.py
iotprovision/winc/wincupgrade.py
iotprovision-2.12.4.20.dist-info/LICENSE.txt
iotprovision-2.12.4.20.dist-info/METADATA
iotprovision-2.12.4.20.dist-info/WHEEL
iotprovision-2.12.4.20.dist-info/entry_points.txt
iotprovision-2.12.4.20.dist-info/top_level.txt
iotprovision-2.12.4.20.dist-info/RECORD
