Metadata-Version: 2.1
Name: iotprovision
Version: 2.12.4.20
Summary: Collection of tools for cloud provisioning of Microchip IoT kits
Author-email: Microchip Technology <support@microchip.com>
License: MIT
Project-URL: Homepage, https://github.com/microchip-pic-avr-tools/iotprovision
Keywords: Microchip,AWS,AVR-IOT,PIC-IOT,SAM-IOT
Classifier: Development Status :: 5 - Production/Stable
Classifier: Intended Audience :: Developers
Classifier: Topic :: Software Development :: Embedded Systems
Classifier: Programming Language :: Python :: 3
Classifier: Programming Language :: Python :: 3.8
Classifier: Programming Language :: Python :: 3.9
Classifier: Programming Language :: Python :: 3.10
Classifier: Programming Language :: Python :: 3.11
Classifier: Operating System :: Microsoft :: Windows
Classifier: Operating System :: POSIX :: Linux
Classifier: Operating System :: MacOS
Classifier: License :: OSI Approved :: MIT License
Requires-Python: >=3.8
License-File: LICENSE.txt
Requires-Dist: pytz
Requires-Dist: cryptography
Requires-Dist: pyOpenSSL
Requires-Dist: packaging >=20.0
Requires-Dist: pyyaml
Requires-Dist: appdirs
Requires-Dist: pyedbglib >=2.22
Requires-Dist: pymcuprog >=3.7
Requires-Dist: pydebuggerupgrade >=3.4
Requires-Dist: pykitcommander >=2.7.7
Requires-Dist: pytrustplatform >=0.15
Requires-Dist: pyawsutils >=1.2
Requires-Dist: pyazureutils >=0.8
Requires-Dist: pydebuggerconfig >=3.8.3
Requires-Dist: pysequansutils >=2.3.0
Provides-Extra: dev
Requires-Dist: pylint >=2.15 ; extra == 'dev'
Provides-Extra: doc
Requires-Dist: mock ; extra == 'doc'
Requires-Dist: sphinx ; extra == 'doc'
Provides-Extra: test
Requires-Dist: mock ; extra == 'test'
Requires-Dist: pytest ; extra == 'test'
